clickhouse_query/__init__.py
clickhouse_query/config.py
clickhouse_query/functions.py
clickhouse_query/mixins.py
clickhouse_query/utils.py
clickhouse_query/core/__init__.py
clickhouse_query/core/expressions.py
clickhouse_query/core/functions.py
clickhouse_query/core/queryset.py
clickhouse_query/core/subquery.py
clickhouse_query-0.1.2.dist-info/licenses/LICENSE
clickhouse_query-0.1.2.dist-info/METADATA
clickhouse_query-0.1.2.dist-info/WHEEL
clickhouse_query-0.1.2.dist-info/top_level.txt
clickhouse_query-0.1.2.dist-info/RECORD
