Metadata-Version: 2.4
Name: clickhouse-query
Version: 0.1.2
Summary: clickhouse query
Home-page: https://github.com/mehrh8/clickhouse-query
Author: Mehrshad Hosseini
Author-email: mehrh8@gmail.com
Project-URL: Bug Tracker, https://github.com/mehrh8/clickhouse-query/issues
Classifier: Programming Language :: Python :: 3
Classifier: License :: OSI Approved :: MIT License
Classifier: Operating System :: OS Independent
Requires-Python: >=3.6
License-File: LICENSE
Dynamic: author
Dynamic: author-email
Dynamic: classifier
Dynamic: description
Dynamic: description-content-type
Dynamic: home-page
Dynamic: license-file
Dynamic: project-url
Dynamic: requires-python
Dynamic: summary
